lona/__init__.py
lona/__main__.py
lona/_json.py
lona/app.py
lona/buckets.py
lona/channels.py
lona/compat.py
lona/connection.py
lona/default_routes.py
lona/default_settings.py
lona/default_views.py
lona/errors.py
lona/exceptions.py
lona/imports.py
lona/logging.py
lona/middleware_controller.py
lona/protocol.py
lona/pytest.py
lona/request.py
lona/responses.py
lona/routing.py
lona/server.py
lona/settings.py
lona/state.py
lona/static_file_loader.py
lona/static_files.py
lona/templating.py
lona/unique_ids.py
lona/view.py
lona/view_loader.py
lona/view_runtime.py
lona/view_runtime_controller.py
lona/warnings.py
lona/worker_pool.py
lona/client/_lona/client/context.js
lona/client/_lona/client/dom-renderer.js
lona/client/_lona/client/dom-updater.js
lona/client/_lona/client/input-events.js
lona/client/_lona/client/lona.js
lona/client/_lona/client/widget-data-updater.js
lona/client/_lona/client/window.js
lona/client2/_lona/client2/context.js
lona/client2/_lona/client2/input-events.js
lona/client2/_lona/client2/lona.js
lona/client2/_lona/client2/rendering-engine.js
lona/client2/_lona/client2/widget.js
lona/client2/_lona/client2/window-shim.js
lona/client2/_lona/client2/window.js
lona/command_line/__init__.py
lona/command_line/collect_static.py
lona/command_line/handle_command_line.py
lona/command_line/run_server.py
lona/command_line/terminal.py
lona/events/__init__.py
lona/events/event_types.py
lona/events/input_event.py
lona/events/view_event.py
lona/html/__init__.py
lona/html/abstract_node.py
lona/html/attribute_dict.py
lona/html/attribute_list.py
lona/html/document.py
lona/html/mixins.py
lona/html/node.py
lona/html/node_event_list.py
lona/html/node_list.py
lona/html/parsing.py
lona/html/patches.py
lona/html/selector.py
lona/html/text_node.py
lona/html/widget.py
lona/html/widget_data.py
lona/html/widgets.py
lona/html/nodes/__init__.py
lona/html/nodes/content_sectioning.py
lona/html/nodes/demarcating_edits.py
lona/html/nodes/document_metadata.py
lona-1.16.2.dist-info/LICENSE.txt
lona-1.16.2.dist-info/METADATA
lona-1.16.2.dist-info/WHEEL
lona-1.16.2.dist-info/entry_points.txt
lona-1.16.2.dist-info/top_level.txt
lona-1.16.2.dist-info/RECORD
