Metadata-Version: 2.1
Name: lona
Version: 1.16.2
Summary: Write responsive web apps in full python
Author-email: Florian Scherf <mail@florianscherf.de>
License: MIT License
Project-URL: Homepage, https://lona-web.org
Project-URL: Repository, https://github.com/lona-web-org/lona
Project-URL: Bug Tracker, https://github.com/lona-web-org/lona/issues
Classifier: Development Status :: 5 - Production/Stable
Classifier: Environment :: Web Environment
Classifier: Framework :: AsyncIO
Classifier: Framework :: Django
Classifier: Framework :: Pytest
Classifier: License :: OSI Approved :: MIT License
Classifier: Natural Language :: English
Classifier: Operating System :: Unix
Classifier: Programming Language :: JavaScript
Classifier: Programming Language :: Python :: 3 :: Only
Classifier: Topic :: Internet
Classifier: Topic :: Internet :: WWW/HTTP
Classifier: Topic :: Internet :: WWW/HTTP :: Dynamic Content
Requires-Python: >=3.8
License-File: LICENSE.txt
Requires-Dist: aiohttp <4,>=3
Requires-Dist: watchfiles
Requires-Dist: jinja2
Requires-Dist: rlpython
Requires-Dist: typing-extensions
Provides-Extra: dev
Requires-Dist: tox ; extra == 'dev'
Provides-Extra: lint
Requires-Dist: aiohttp <4,>=3 ; extra == 'lint'
Requires-Dist: jinja2 ; extra == 'lint'
Requires-Dist: rlpython ; extra == 'lint'
Requires-Dist: typing-extensions ; extra == 'lint'
Requires-Dist: coverage ; extra == 'lint'
Requires-Dist: flake8 ==7.0.0 ; extra == 'lint'
Requires-Dist: flake8-2020 ==1.8.1 ; extra == 'lint'
Requires-Dist: flake8-bugbear ==24.2.6 ; extra == 'lint'
Requires-Dist: flake8-commas ==2.1.0 ; extra == 'lint'
Requires-Dist: flake8-comprehensions ==3.14.0 ; extra == 'lint'
Requires-Dist: flake8-length ==0.3.1 ; extra == 'lint'
Requires-Dist: flake8-logging-format ==0.9.0 ; extra == 'lint'
Requires-Dist: flake8-mutable ==1.2.0 ; extra == 'lint'
Requires-Dist: flake8-noqa ==1.4.0 ; extra == 'lint'
Requires-Dist: flake8-pytest-style ==1.7.2 ; extra == 'lint'
Requires-Dist: flake8-quotes ==3.4.0 ; extra == 'lint'
Requires-Dist: flake8-use-fstring ==1.4 ; extra == 'lint'
Requires-Dist: mypy ==1.9.0 ; extra == 'lint'
Requires-Dist: isort ==5.13.2 ; extra == 'lint'
Requires-Dist: pytest ==8.1.1 ; extra == 'lint'
Provides-Extra: packaging
Requires-Dist: build ; extra == 'packaging'
Requires-Dist: twine ; extra == 'packaging'
Provides-Extra: test
Requires-Dist: aiohttp <4,>=3 ; extra == 'test'
Requires-Dist: jinja2 ; extra == 'test'
Requires-Dist: rlpython ; extra == 'test'
Requires-Dist: typing-extensions ; extra == 'test'
Requires-Dist: coverage ==7.4.4 ; extra == 'test'
Requires-Dist: pytest ==8.1.1 ; extra == 'test'
Requires-Dist: pytest-aiohttp ==1.0.5 ; extra == 'test'
Requires-Dist: pytest-mock ==3.14.0 ; extra == 'test'
Requires-Dist: pytest-timeout ==2.3.1 ; extra == 'test'
Requires-Dist: playwright ==1.40.0 ; extra == 'test'
